README.rst
setup.py
alisuretool/Tools.py
alisuretool/__init__.py
alisuretool.egg-info/PKG-INFO
alisuretool.egg-info/SOURCES.txt
alisuretool.egg-info/dependency_links.txt
alisuretool.egg-info/top_level.txt